plotbox2.py
plotbox2-0.1.1.data/data/Lib/site-packages/plotbox/font/AvantGarGotItcTEE.ttf
plotbox2-0.1.1.data/data/Lib/site-packages/plotbox/font/Futura Lt BT.ttf
plotbox2-0.1.1.data/data/Lib/site-packages/plotbox/font/HomeStoreRegular.ttf
plotbox2-0.1.1.data/data/Lib/site-packages/plotbox/font/Microsoft-Yahei-UI-Light.ttc
plotbox2-0.1.1.data/data/Lib/site-packages/plotbox/font/kaitiGB2312.ttf
plotbox2-0.1.1.data/data/Lib/site-packages/plotbox/font/youyuan.TTF
plotbox2-0.1.1.dist-info/DESCRIPTION.rst
plotbox2-0.1.1.dist-info/METADATA
plotbox2-0.1.1.dist-info/RECORD
plotbox2-0.1.1.dist-info/WHEEL
plotbox2-0.1.1.dist-info/metadata.json
plotbox2-0.1.1.dist-info/top_level.txt
